clinspector/__init__.py
clinspector/help_providers/__init__.py
clinspector/help_providers/base.py
clinspector/help_providers/man_pages.py
clinspector/help_providers/tldr_pages.py
clinspector/introspect/__init__.py
clinspector/introspect/cliparser.py
clinspector/introspect/introspect_argparse.py
clinspector/introspect/introspect_cappa.py
clinspector/introspect/introspect_cleo.py
clinspector/introspect/introspect_click.py
clinspector/introspect/introspect_cyclopts.py
clinspector/introspect/introspect_typer.py
clinspector/introspect/markdown.py
clinspector/log.py
clinspector/models/__init__.py
clinspector/models/commandinfo.py
clinspector/models/param.py
clinspector/py.typed
clinspector/synthesis/__init__.py
clinspector/synthesis/synth_argparse.py
clinspector/synthesis/synth_cappa.py
clinspector/synthesis/synth_cleo.py
clinspector/synthesis/synth_click.py
clinspector/synthesis/synth_typer.py
clinspector-1.0.1.dist-info/licenses/LICENSE
clinspector-1.0.1.dist-info/WHEEL
clinspector-1.0.1.dist-info/METADATA
clinspector-1.0.1.dist-info/RECORD
