Metadata-Version: 2.4
Name: clinspector
Version: 1.0.1
Summary: A library to parse CLI output into structured data.
Keywords: 
Author: Philipp Temminghoff
Author-email: Philipp Temminghoff <philipptemminghoff@googlemail.com>
License-Expression: MIT
License-File: LICENSE
Classifier: Development Status :: 4 - Beta
Classifier: Intended Audience :: Developers
Classifier: Operating System :: OS Independent
Classifier: Programming Language :: Python :: 3
Classifier: Programming Language :: Python :: 3 :: Only
Classifier: Programming Language :: Python :: 3.12
Classifier: Programming Language :: Python :: 3.13
Classifier: Programming Language :: Python :: 3.14
Classifier: Topic :: Documentation
Classifier: Topic :: Software Development
Classifier: Topic :: Utilities
Classifier: Typing :: Typed
Requires-Dist: anyenv[httpx]>=0.5.0
Requires-Dist: schemez>=0.3.0
Requires-Dist: click ; extra == 'all'
Requires-Dist: typer ; extra == 'all'
Requires-Dist: cappa ; extra == 'all'
Requires-Dist: cleo ; extra == 'all'
Requires-Dist: cappa ; extra == 'cappa'
Requires-Dist: cleo ; extra == 'cleo'
Requires-Dist: click ; extra == 'click'
Requires-Dist: cyclopts ; extra == 'cyclopts'
Requires-Dist: hishel>=0.1.1 ; extra == 'man-pages'
Requires-Dist: httpx ; extra == 'man-pages'
Requires-Dist: tldr ; extra == 'tldr'
Requires-Dist: typer ; extra == 'typer'
Requires-Python: >=3.13
Project-URL: Code coverage, https://app.codecov.io/gh/phil65/clinspector
Project-URL: Discussions, https://github.com/phil65/clinspector/discussions
Project-URL: Documentation, https://phil65.github.io/clinspector/
Project-URL: Issues, https://github.com/phil65/clinspector/issues
Project-URL: Source, https://github.com/phil65/clinspector
Provides-Extra: all
Provides-Extra: cappa
Provides-Extra: cleo
Provides-Extra: click
Provides-Extra: cyclopts
Provides-Extra: man-pages
Provides-Extra: tldr
Provides-Extra: typer
